LabuladongDeSuanfaXiaochaoFix1/README.md
LabuladongDeSuanfaXiaochaoFix1/__init__.py
LabuladongDeSuanfaXiaochaoFix1/__main__.py
LabuladongDeSuanfaXiaochaoFix1/file.epub
LabuladongDeSuanfaXiaochaoFix1/index.html
LabuladongDeSuanfaXiaochaoFix1/css/__init__.py
LabuladongDeSuanfaXiaochaoFix1/css/annotations.css
LabuladongDeSuanfaXiaochaoFix1/css/main.css
LabuladongDeSuanfaXiaochaoFix1/css/normalize.css
LabuladongDeSuanfaXiaochaoFix1/css/popup.css
LabuladongDeSuanfaXiaochaoFix1/font/__init__.py
LabuladongDeSuanfaXiaochaoFix1/font/fontello.eot
LabuladongDeSuanfaXiaochaoFix1/font/fontello.svg
LabuladongDeSuanfaXiaochaoFix1/font/fontello.ttf
LabuladongDeSuanfaXiaochaoFix1/font/fontello.woff
LabuladongDeSuanfaXiaochaoFix1/img/__init__.py
LabuladongDeSuanfaXiaochaoFix1/img/annotator-glyph-sprite.png
LabuladongDeSuanfaXiaochaoFix1/img/annotator-icon-sprite.png
LabuladongDeSuanfaXiaochaoFix1/img/apple-touch-icon.png
LabuladongDeSuanfaXiaochaoFix1/img/cancelfullscreen.png
LabuladongDeSuanfaXiaochaoFix1/img/close.png
LabuladongDeSuanfaXiaochaoFix1/img/fullscreen.png
LabuladongDeSuanfaXiaochaoFix1/img/loader.gif
LabuladongDeSuanfaXiaochaoFix1/img/menu-icon.png
LabuladongDeSuanfaXiaochaoFix1/img/save.png
LabuladongDeSuanfaXiaochaoFix1/img/saved.png
LabuladongDeSuanfaXiaochaoFix1/img/settings-s.png
LabuladongDeSuanfaXiaochaoFix1/img/settings.png
LabuladongDeSuanfaXiaochaoFix1/img/star.png
LabuladongDeSuanfaXiaochaoFix1/js/__init__.py
LabuladongDeSuanfaXiaochaoFix1/js/epub.js
LabuladongDeSuanfaXiaochaoFix1/js/epub.min.js
LabuladongDeSuanfaXiaochaoFix1/js/epub.min.map
LabuladongDeSuanfaXiaochaoFix1/js/hooks.min.js
LabuladongDeSuanfaXiaochaoFix1/js/hooks.min.map
LabuladongDeSuanfaXiaochaoFix1/js/reader.js
LabuladongDeSuanfaXiaochaoFix1/js/reader.js.map
LabuladongDeSuanfaXiaochaoFix1/js/reader.min.js
LabuladongDeSuanfaXiaochaoFix1/js/reader.min.map
LabuladongDeSuanfaXiaochaoFix1/js/hooks/__init__.py
LabuladongDeSuanfaXiaochaoFix1/js/hooks/extensions/__init__.py
labuladong_de_suanfa_xiaochao_fix1-2025.3.24.0.dist-info/METADATA
labuladong_de_suanfa_xiaochao_fix1-2025.3.24.0.dist-info/WHEEL
labuladong_de_suanfa_xiaochao_fix1-2025.3.24.0.dist-info/entry_points.txt
labuladong_de_suanfa_xiaochao_fix1-2025.3.24.0.dist-info/top_level.txt
labuladong_de_suanfa_xiaochao_fix1-2025.3.24.0.dist-info/RECORD
